latex_builder/__init__.py
latex_builder/cli/__init__.py
latex_builder/cli/main.py
latex_builder/cli/parser.py
latex_builder/config/__init__.py
latex_builder/config/settings.py
latex_builder/diff/__init__.py
latex_builder/diff/generator.py
latex_builder/git/__init__.py
latex_builder/git/repository.py
latex_builder/git/revision.py
latex_builder/latex/__init__.py
latex_builder/latex/processor.py
latex_builder/utils/__init__.py
latex_builder/utils/command.py
latex_builder/utils/logging.py
latex_builder-0.0.15.dist-info/METADATA
latex_builder-0.0.15.dist-info/WHEEL
latex_builder-0.0.15.dist-info/entry_points.txt
latex_builder-0.0.15.dist-info/top_level.txt
latex_builder-0.0.15.dist-info/RECORD
