Metadata-Version: 2.4
Name: latex-builder
Version: 0.0.15
Summary: A tool for building LaTeX documents with Git integration and diff generation
Requires-Python: >=3.11
Requires-Dist: gitpython>=3.1.44
Requires-Dist: pygments>=2.19.1
Requires-Dist: rich>=14.0.0
Requires-Dist: ruff>=0.11.5
Requires-Dist: semver>=3.0.4
Requires-Dist: structlog>=24.0.0
